{
	"class" : {
		"defaultMaxItems" : "lr 10/7/2010 15:36",
		"groupLabel" : "lr 9/12/2009 12:49",
		"isAbstract" : "lr 9/12/2009 12:49",
		"label" : "lr 10/7/2010 13:24" },
	"instance" : {
		"descriptionDropdownList" : "NickAger 1/30/2012 17:19",
		"descriptionExampleText" : "NickAger 1/30/2012 17:19",
		"descriptionStructure" : "NickAger 1/30/2012 17:19",
		"dropdownList" : "lr 9/12/2009 12:49",
		"exampleText" : "NickAger 1/30/2012 17:20",
		"exampleText:" : "NickAger 1/30/2012 17:21",
		"renderContentOn:" : "NickAger 11/14/2010 22:42",
		"structure" : "NickAger 1/30/2012 17:20",
		"structure:" : "NickAger 1/30/2012 17:20",
		"structuresFor:" : "NickAger 11/14/2010 22:41",
		"updateRoot:" : "NickAger 11/14/2010 22:38" } }
